{"info": {"codmunicipio": "1711506", "nome": "Jaú do Tocantins", "uf": "TO", "regiao": "Norte", "lat": -9.5584, "lon": -45.6182, "populacao": 8412, "icvs": 66.69, "sub_desfechos": 59.96, "sub_acesso": 74.51, "sub_qualidade": 66.5, "icvs_quintil": 5, "cluster": 3}, "icvs_historico": [{"ano": 2014, "icvs": 65.79, "icvs_quintil": 4, "sub_desfechos": 60.79, "sub_acesso": 71.52, "sub_qualidade": 65.78}, {"ano": 2015, "icvs": 69.57, "icvs_quintil": 4, "sub_desfechos": 76.87, "sub_acesso": 57.72, "sub_qualidade": 74.46}, {"ano": 2016, "icvs": 64.44, "icvs_quintil": 4, "sub_desfechos": 54.85, "sub_acesso": 78.64, "sub_qualidade": 59.9}, {"ano": 2017, "icvs": 71.39, "icvs_quintil": 4, "sub_desfechos": 79.48, "sub_acesso": 69.47, "sub_qualidade": 61.11}, {"ano": 2018, "icvs": 37.41, "icvs_quintil": 2, "sub_desfechos": 27.77, "sub_acesso": 38.72, "sub_qualidade": 51.0}, {"ano": 2019, "icvs": 88.52, "icvs_quintil": 5, "sub_desfechos": 96.48, "sub_acesso": 81.45, "sub_qualidade": 85.7}, {"ano": 2020, "icvs": 62.76, "icvs_quintil": 4, "sub_desfechos": 52.36, "sub_acesso": 66.78, "sub_qualidade": 73.76}, {"ano": 2021, "icvs": 53.01, "icvs_quintil": 3, "sub_desfechos": 53.73, "sub_acesso": 49.91, "sub_qualidade": 56.2}, {"ano": 2022, "icvs": 58.58, "icvs_quintil": 3, "sub_desfechos": 61.31, "sub_acesso": 54.84, "sub_qualidade": 59.45}, {"ano": 2023, "icvs": 61.13, "icvs_quintil": 4, "sub_desfechos": 64.81, "sub_acesso": 67.12, "sub_qualidade": 46.84}], "indicadores": [{"ano": 2023, "indicador": "tmi", "valor": 0.7517, "valor_suavizado": 0.7163}, {"ano": 2023, "indicador": "rmm", "valor": 0.8057, "valor_suavizado": 0.8317}, {"ano": 2023, "indicador": "apvp_taxa", "valor": 0.6101, "valor_suavizado": 0.5924}, {"ano": 2023, "indicador": "mort_prematura_dcnt", "valor": 0.7034, "valor_suavizado": 0.7221}, {"ano": 2023, "indicador": "proporcao_obitos_evitaveis", "valor": 0.8142, "valor_suavizado": 0.8131}, {"ano": 2023, "indicador": "cobertura_esf_inv", "valor": 0.9099, "valor_suavizado": 0.9327}, {"ano": 2023, "indicador": "cobertura_acs_inv", "valor": 0.9179, "valor_suavizado": 0.8965}, {"ano": 2023, "indicador": "leitos_sus_inv", "valor": 0.4364, "valor_suavizado": 0.4308}, {"ano": 2023, "indicador": "medicos_inv", "valor": 0.8503, "valor_suavizado": 0.8355}, {"ano": 2023, "indicador": "distancia_hospital", "valor": 0.6814, "valor_suavizado": 0.6624}, {"ano": 2023, "indicador": "taxa_icsap", "valor": 1, "valor_suavizado": 1}, {"ano": 2023, "indicador": "taxa_cesareas_sus", "valor": 0.8113, "valor_suavizado": 0.813}, {"ano": 2023, "indicador": "prenatal_inadequado", "valor": 0.7517, "valor_suavizado": 0.7841}, {"ano": 2023, "indicador": "internacao_dm", "valor": 0.7916, "valor_suavizado": 0.7823}, {"ano": 2023, "indicador": "obitos_sem_assistencia", "valor": 0.9394, "valor_suavizado": 0.9343}]}