{"info": {"codmunicipio": "2201408", "nome": "Barro Duro", "uf": "PI", "regiao": "Nordeste", "lat": -6.9147, "lon": -41.7272, "populacao": 218212, "icvs": 49.58, "sub_desfechos": 48.91, "sub_acesso": 40.68, "sub_qualidade": 63.09, "icvs_quintil": 3, "cluster": 1}, "icvs_historico": [{"ano": 2014, "icvs": 58.97, "icvs_quintil": 3, "sub_desfechos": 61.82, "sub_acesso": 52.98, "sub_qualidade": 62.8}, {"ano": 2015, "icvs": 80.53, "icvs_quintil": 5, "sub_desfechos": 90.73, "sub_acesso": 65.66, "sub_qualidade": 85.05}, {"ano": 2016, "icvs": 88.89, "icvs_quintil": 5, "sub_desfechos": 82.31, "sub_acesso": 100, "sub_qualidade": 83.88}, {"ano": 2017, "icvs": 53.05, "icvs_quintil": 3, "sub_desfechos": 55.08, "sub_acesso": 43.45, "sub_qualidade": 63.25}, {"ano": 2018, "icvs": 70.55, "icvs_quintil": 4, "sub_desfechos": 56.93, "sub_acesso": 80.7, "sub_qualidade": 78.13}, {"ano": 2019, "icvs": 83.91, "icvs_quintil": 5, "sub_desfechos": 88.91, "sub_acesso": 69.83, "sub_qualidade": 95.63}, {"ano": 2020, "icvs": 37.07, "icvs_quintil": 2, "sub_desfechos": 42.44, "sub_acesso": 35.5, "sub_qualidade": 30.68}, {"ano": 2021, "icvs": 63.7, "icvs_quintil": 4, "sub_desfechos": 65.24, "sub_acesso": 59.67, "sub_qualidade": 66.85}, {"ano": 2022, "icvs": 44.96, "icvs_quintil": 3, "sub_desfechos": 52.49, "sub_acesso": 39.47, "sub_qualidade": 40.6}, {"ano": 2023, "icvs": 42.93, "icvs_quintil": 3, "sub_desfechos": 43.82, "sub_acesso": 39.33, "sub_qualidade": 46.56}], "indicadores": [{"ano": 2023, "indicador": "tmi", "valor": 0.5623, "valor_suavizado": 0.5936}, {"ano": 2023, "indicador": "rmm", "valor": 0.4609, "valor_suavizado": 0.4572}, {"ano": 2023, "indicador": "apvp_taxa", "valor": 0.4636, "valor_suavizado": 0.4715}, {"ano": 2023, "indicador": "mort_prematura_dcnt", "valor": 0.6448, "valor_suavizado": 0.6332}, {"ano": 2023, "indicador": "proporcao_obitos_evitaveis", "valor": 0.4996, "valor_suavizado": 0.5068}, {"ano": 2023, "indicador": "cobertura_esf_inv", "valor": 0.89, "valor_suavizado": 0.8527}, {"ano": 2023, "indicador": "cobertura_acs_inv", "valor": 0.6506, "valor_suavizado": 0.6713}, {"ano": 2023, "indicador": "leitos_sus_inv", "valor": 0.5602, "valor_suavizado": 0.5558}, {"ano": 2023, "indicador": "medicos_inv", "valor": 0.6018, "valor_suavizado": 0.6287}, {"ano": 2023, "indicador": "distancia_hospital", "valor": 0.715, "valor_suavizado": 0.7309}, {"ano": 2023, "indicador": "taxa_icsap", "valor": 1, "valor_suavizado": 0.9909}, {"ano": 2023, "indicador": "taxa_cesareas_sus", "valor": 0.5715, "valor_suavizado": 0.563}, {"ano": 2023, "indicador": "prenatal_inadequado", "valor": 0.5785, "valor_suavizado": 0.5912}, {"ano": 2023, "indicador": "internacao_dm", "valor": 0.7253, "valor_suavizado": 0.7436}, {"ano": 2023, "indicador": "obitos_sem_assistencia", "valor": 0.6424, "valor_suavizado": 0.6255}]}