{"info": {"codmunicipio": "2204105", "nome": "Francisco Ayres", "uf": "PI", "regiao": "Nordeste", "lat": -7.8684, "lon": -43.5709, "populacao": 1361, "icvs": 72.02, "sub_desfechos": 64.38, "sub_acesso": 79.53, "sub_qualidade": 73.71, "icvs_quintil": 5, "cluster": 3}, "icvs_historico": [{"ano": 2014, "icvs": 50.15, "icvs_quintil": 3, "sub_desfechos": 68.5, "sub_acesso": 28.53, "sub_qualidade": 51.06}, {"ano": 2015, "icvs": 46.94, "icvs_quintil": 3, "sub_desfechos": 53.85, "sub_acesso": 39.26, "sub_qualidade": 46.64}, {"ano": 2016, "icvs": 91.71, "icvs_quintil": 5, "sub_desfechos": 89.93, "sub_acesso": 96.92, "sub_qualidade": 87.27}, {"ano": 2017, "icvs": 62.21, "icvs_quintil": 4, "sub_desfechos": 52.27, "sub_acesso": 60.39, "sub_qualidade": 80.65}, {"ano": 2018, "icvs": 54.56, "icvs_quintil": 3, "sub_desfechos": 61.86, "sub_acesso": 39.66, "sub_qualidade": 63.74}, {"ano": 2019, "icvs": 50.51, "icvs_quintil": 3, "sub_desfechos": 53.85, "sub_acesso": 49.97, "sub_qualidade": 45.9}, {"ano": 2020, "icvs": 85.76, "icvs_quintil": 5, "sub_desfechos": 93.81, "sub_acesso": 76.9, "sub_qualidade": 85.29}, {"ano": 2021, "icvs": 57.16, "icvs_quintil": 3, "sub_desfechos": 52.94, "sub_acesso": 60.22, "sub_qualidade": 59.64}, {"ano": 2022, "icvs": 69.25, "icvs_quintil": 4, "sub_desfechos": 60.84, "sub_acesso": 88.09, "sub_qualidade": 56.31}, {"ano": 2023, "icvs": 53.77, "icvs_quintil": 3, "sub_desfechos": 52.05, "sub_acesso": 63.12, "sub_qualidade": 43.45}], "indicadores": [{"ano": 2023, "indicador": "tmi", "valor": 0.3883, "valor_suavizado": 0.4039}, {"ano": 2023, "indicador": "rmm", "valor": 0.6763, "valor_suavizado": 0.6175}, {"ano": 2023, "indicador": "apvp_taxa", "valor": 0.6862, "valor_suavizado": 0.6969}, {"ano": 2023, "indicador": "mort_prematura_dcnt", "valor": 0.6211, "valor_suavizado": 0.6002}, {"ano": 2023, "indicador": "proporcao_obitos_evitaveis", "valor": 0.4277, "valor_suavizado": 0.3988}, {"ano": 2023, "indicador": "cobertura_esf_inv", "valor": 0.5037, "valor_suavizado": 0.536}, {"ano": 2023, "indicador": "cobertura_acs_inv", "valor": 0.7536, "valor_suavizado": 0.6994}, {"ano": 2023, "indicador": "leitos_sus_inv", "valor": 0.5912, "valor_suavizado": 0.5779}, {"ano": 2023, "indicador": "medicos_inv", "valor": 0.5995, "valor_suavizado": 0.571}, {"ano": 2023, "indicador": "distancia_hospital", "valor": 0.597, "valor_suavizado": 0.5689}, {"ano": 2023, "indicador": "taxa_icsap", "valor": 0.384, "valor_suavizado": 0.3726}, {"ano": 2023, "indicador": "taxa_cesareas_sus", "valor": 0.452, "valor_suavizado": 0.4256}, {"ano": 2023, "indicador": "prenatal_inadequado", "valor": 0.5757, "valor_suavizado": 0.586}, {"ano": 2023, "indicador": "internacao_dm", "valor": 0.5444, "valor_suavizado": 0.5508}, {"ano": 2023, "indicador": "obitos_sem_assistencia", "valor": 0.4076, "valor_suavizado": 0.4247}]}