{"info": {"codmunicipio": "2210904", "nome": "Socorro do Piauí", "uf": "PI", "regiao": "Nordeste", "lat": -9.6451, "lon": -44.7366, "populacao": 16398, "icvs": 58.62, "sub_desfechos": 59.38, "sub_acesso": 60.59, "sub_qualidade": 54.65, "icvs_quintil": 4, "cluster": 3}, "icvs_historico": [{"ano": 2014, "icvs": 72.09, "icvs_quintil": 4, "sub_desfechos": 84.49, "sub_acesso": 67.42, "sub_qualidade": 58.8}, {"ano": 2015, "icvs": 47.24, "icvs_quintil": 3, "sub_desfechos": 55.66, "sub_acesso": 49.73, "sub_qualidade": 30.27}, {"ano": 2016, "icvs": 77.97, "icvs_quintil": 4, "sub_desfechos": 81.95, "sub_acesso": 76.74, "sub_qualidade": 73.34}, {"ano": 2017, "icvs": 49.34, "icvs_quintil": 3, "sub_desfechos": 43.73, "sub_acesso": 62.49, "sub_qualidade": 39.9}, {"ano": 2018, "icvs": 64.78, "icvs_quintil": 4, "sub_desfechos": 56.52, "sub_acesso": 76.04, "sub_qualidade": 62.23}, {"ano": 2019, "icvs": 64.88, "icvs_quintil": 4, "sub_desfechos": 73.97, "sub_acesso": 56.12, "sub_qualidade": 62.6}, {"ano": 2020, "icvs": 87.51, "icvs_quintil": 5, "sub_desfechos": 83.95, "sub_acesso": 100, "sub_qualidade": 75.72}, {"ano": 2021, "icvs": 69.79, "icvs_quintil": 4, "sub_desfechos": 63.76, "sub_acesso": 81.88, "sub_qualidade": 62.5}, {"ano": 2022, "icvs": 86.24, "icvs_quintil": 5, "sub_desfechos": 98.06, "sub_acesso": 72.38, "sub_qualidade": 86.73}, {"ano": 2023, "icvs": 75.03, "icvs_quintil": 4, "sub_desfechos": 86.39, "sub_acesso": 68.15, "sub_qualidade": 66.49}], "indicadores": [{"ano": 2023, "indicador": "tmi", "valor": 0.541, "valor_suavizado": 0.4992}, {"ano": 2023, "indicador": "rmm", "valor": 0.8218, "valor_suavizado": 0.8419}, {"ano": 2023, "indicador": "apvp_taxa", "valor": 0.8915, "valor_suavizado": 0.9233}, {"ano": 2023, "indicador": "mort_prematura_dcnt", "valor": 0.6697, "valor_suavizado": 0.6841}, {"ano": 2023, "indicador": "proporcao_obitos_evitaveis", "valor": 0.9694, "valor_suavizado": 0.9699}, {"ano": 2023, "indicador": "cobertura_esf_inv", "valor": 0.6038, "valor_suavizado": 0.6016}, {"ano": 2023, "indicador": "cobertura_acs_inv", "valor": 0.414, "valor_suavizado": 0.4648}, {"ano": 2023, "indicador": "leitos_sus_inv", "valor": 0.6818, "valor_suavizado": 0.6826}, {"ano": 2023, "indicador": "medicos_inv", "valor": 0.4975, "valor_suavizado": 0.4715}, {"ano": 2023, "indicador": "distancia_hospital", "valor": 0.7032, "valor_suavizado": 0.7077}, {"ano": 2023, "indicador": "taxa_icsap", "valor": 0.7153, "valor_suavizado": 0.7131}, {"ano": 2023, "indicador": "taxa_cesareas_sus", "valor": 0.4853, "valor_suavizado": 0.5005}, {"ano": 2023, "indicador": "prenatal_inadequado", "valor": 0.7337, "valor_suavizado": 0.7193}, {"ano": 2023, "indicador": "internacao_dm", "valor": 0.3269, "valor_suavizado": 0.3482}, {"ano": 2023, "indicador": "obitos_sem_assistencia", "valor": 0.6117, "valor_suavizado": 0.5895}]}