{"info": {"codmunicipio": "2310902", "nome": "Piquet Carneiro", "uf": "CE", "regiao": "Nordeste", "lat": -4.2651, "lon": -38.0273, "populacao": 8293, "icvs": 17.87, "sub_desfechos": 39.92, "sub_acesso": 0, "sub_qualidade": 7.61, "icvs_quintil": 1, "cluster": 3}, "icvs_historico": [{"ano": 2014, "icvs": 65.15, "icvs_quintil": 4, "sub_desfechos": 53.99, "sub_acesso": 77.29, "sub_qualidade": 65.99}, {"ano": 2015, "icvs": 32.25, "icvs_quintil": 2, "sub_desfechos": 26.17, "sub_acesso": 36.37, "sub_qualidade": 36.21}, {"ano": 2016, "icvs": 67.46, "icvs_quintil": 4, "sub_desfechos": 73.95, "sub_acesso": 54.81, "sub_qualidade": 74.78}, {"ano": 2017, "icvs": 92.21, "icvs_quintil": 5, "sub_desfechos": 88.22, "sub_acesso": 91.2, "sub_qualidade": 100}, {"ano": 2018, "icvs": 64.0, "icvs_quintil": 4, "sub_desfechos": 68.21, "sub_acesso": 53.67, "sub_qualidade": 71.73}, {"ano": 2019, "icvs": 66.79, "icvs_quintil": 4, "sub_desfechos": 72.05, "sub_acesso": 67.06, "sub_qualidade": 58.0}, {"ano": 2020, "icvs": 88.32, "icvs_quintil": 5, "sub_desfechos": 100, "sub_acesso": 79.63, "sub_qualidade": 81.78}, {"ano": 2021, "icvs": 48.67, "icvs_quintil": 3, "sub_desfechos": 59.22, "sub_acesso": 32.78, "sub_qualidade": 54.03}, {"ano": 2022, "icvs": 96.75, "icvs_quintil": 5, "sub_desfechos": 94.98, "sub_acesso": 100, "sub_qualidade": 95.02}, {"ano": 2023, "icvs": 48.0, "icvs_quintil": 3, "sub_desfechos": 45.98, "sub_acesso": 48.48, "sub_qualidade": 50.56}], "indicadores": [{"ano": 2023, "indicador": "tmi", "valor": 0.7489, "valor_suavizado": 0.7371}, {"ano": 2023, "indicador": "rmm", "valor": 1, "valor_suavizado": 1}, {"ano": 2023, "indicador": "apvp_taxa", "valor": 0.96, "valor_suavizado": 0.9521}, {"ano": 2023, "indicador": "mort_prematura_dcnt", "valor": 0.6209, "valor_suavizado": 0.6162}, {"ano": 2023, "indicador": "proporcao_obitos_evitaveis", "valor": 0.5514, "valor_suavizado": 0.5245}, {"ano": 2023, "indicador": "cobertura_esf_inv", "valor": 0.6941, "valor_suavizado": 0.6704}, {"ano": 2023, "indicador": "cobertura_acs_inv", "valor": 0.8619, "valor_suavizado": 0.9037}, {"ano": 2023, "indicador": "leitos_sus_inv", "valor": 0.5819, "valor_suavizado": 0.5784}, {"ano": 2023, "indicador": "medicos_inv", "valor": 0.9111, "valor_suavizado": 0.9206}, {"ano": 2023, "indicador": "distancia_hospital", "valor": 0.9428, "valor_suavizado": 0.9532}, {"ano": 2023, "indicador": "taxa_icsap", "valor": 0.8795, "valor_suavizado": 0.8673}, {"ano": 2023, "indicador": "taxa_cesareas_sus", "valor": 0.7885, "valor_suavizado": 0.7757}, {"ano": 2023, "indicador": "prenatal_inadequado", "valor": 0.6491, "valor_suavizado": 0.6502}, {"ano": 2023, "indicador": "internacao_dm", "valor": 0.5228, "valor_suavizado": 0.5261}, {"ano": 2023, "indicador": "obitos_sem_assistencia", "valor": 0.6095, "valor_suavizado": 0.6556}]}