{"info": {"codmunicipio": "2914653", "nome": "Itabela", "uf": "BA", "regiao": "Nordeste", "lat": -12.9348, "lon": -43.4999, "populacao": 17765, "icvs": 27.06, "sub_desfechos": 25.47, "sub_acesso": 21.86, "sub_qualidade": 36.9, "icvs_quintil": 1, "cluster": 3}, "icvs_historico": [{"ano": 2014, "icvs": 47.29, "icvs_quintil": 3, "sub_desfechos": 54.09, "sub_acesso": 37.81, "sub_qualidade": 49.69}, {"ano": 2015, "icvs": 47.82, "icvs_quintil": 3, "sub_desfechos": 33.64, "sub_acesso": 58.9, "sub_qualidade": 55.01}, {"ano": 2016, "icvs": 66.88, "icvs_quintil": 4, "sub_desfechos": 71.62, "sub_acesso": 69.97, "sub_qualidade": 54.98}, {"ano": 2017, "icvs": 51.72, "icvs_quintil": 3, "sub_desfechos": 55.36, "sub_acesso": 45.77, "sub_qualidade": 54.21}, {"ano": 2018, "icvs": 81.78, "icvs_quintil": 5, "sub_desfechos": 78.23, "sub_acesso": 86.33, "sub_qualidade": 81.1}, {"ano": 2019, "icvs": 37.03, "icvs_quintil": 2, "sub_desfechos": 29.78, "sub_acesso": 42.16, "sub_qualidade": 41.46}, {"ano": 2020, "icvs": 73.08, "icvs_quintil": 4, "sub_desfechos": 58.97, "sub_acesso": 88.4, "sub_qualidade": 74.21}, {"ano": 2021, "icvs": 36.39, "icvs_quintil": 2, "sub_desfechos": 24.17, "sub_acesso": 41.21, "sub_qualidade": 49.18}, {"ano": 2022, "icvs": 63.12, "icvs_quintil": 4, "sub_desfechos": 59.74, "sub_acesso": 62.81, "sub_qualidade": 68.96}, {"ano": 2023, "icvs": 79.08, "icvs_quintil": 4, "sub_desfechos": 77.53, "sub_acesso": 91.66, "sub_qualidade": 63.94}], "indicadores": [{"ano": 2023, "indicador": "tmi", "valor": 0.3556, "valor_suavizado": 0.367}, {"ano": 2023, "indicador": "rmm", "valor": 0.5563, "valor_suavizado": 0.5761}, {"ano": 2023, "indicador": "apvp_taxa", "valor": 0.4561, "valor_suavizado": 0.5072}, {"ano": 2023, "indicador": "mort_prematura_dcnt", "valor": 0.245, "valor_suavizado": 0.2571}, {"ano": 2023, "indicador": "proporcao_obitos_evitaveis", "valor": 0.4948, "valor_suavizado": 0.5076}, {"ano": 2023, "indicador": "cobertura_esf_inv", "valor": 0.5409, "valor_suavizado": 0.5345}, {"ano": 2023, "indicador": "cobertura_acs_inv", "valor": 0.2519, "valor_suavizado": 0.2429}, {"ano": 2023, "indicador": "leitos_sus_inv", "valor": 0.7021, "valor_suavizado": 0.74}, {"ano": 2023, "indicador": "medicos_inv", "valor": 0.4955, "valor_suavizado": 0.5072}, {"ano": 2023, "indicador": "distancia_hospital", "valor": 0.6051, "valor_suavizado": 0.6307}, {"ano": 2023, "indicador": "taxa_icsap", "valor": 0.4852, "valor_suavizado": 0.5448}, {"ano": 2023, "indicador": "taxa_cesareas_sus", "valor": 0.5174, "valor_suavizado": 0.5006}, {"ano": 2023, "indicador": "prenatal_inadequado", "valor": 0.8077, "valor_suavizado": 0.8385}, {"ano": 2023, "indicador": "internacao_dm", "valor": 0.6401, "valor_suavizado": 0.6031}, {"ano": 2023, "indicador": "obitos_sem_assistencia", "valor": 0.6535, "valor_suavizado": 0.667}]}