{"info": {"codmunicipio": "2922854", "nome": "Nova Redenção", "uf": "BA", "regiao": "Nordeste", "lat": -13.5251, "lon": -41.8807, "populacao": 1361, "icvs": 48.74, "sub_desfechos": 60.16, "sub_acesso": 32.69, "sub_qualidade": 52.92, "icvs_quintil": 3, "cluster": 3}, "icvs_historico": [{"ano": 2014, "icvs": 83.12, "icvs_quintil": 5, "sub_desfechos": 84.42, "sub_acesso": 82.45, "sub_qualidade": 81.96}, {"ano": 2015, "icvs": 85.87, "icvs_quintil": 5, "sub_desfechos": 100, "sub_acesso": 68.17, "sub_qualidade": 88.04}, {"ano": 2016, "icvs": 48.12, "icvs_quintil": 3, "sub_desfechos": 34.56, "sub_acesso": 61.5, "sub_qualidade": 51.1}, {"ano": 2017, "icvs": 57.15, "icvs_quintil": 3, "sub_desfechos": 61.31, "sub_acesso": 53.88, "sub_qualidade": 55.06}, {"ano": 2018, "icvs": 62.71, "icvs_quintil": 4, "sub_desfechos": 63.45, "sub_acesso": 59.09, "sub_qualidade": 66.59}, {"ano": 2019, "icvs": 73.93, "icvs_quintil": 4, "sub_desfechos": 65.27, "sub_acesso": 86.25, "sub_qualidade": 70.52}, {"ano": 2020, "icvs": 56.33, "icvs_quintil": 3, "sub_desfechos": 46.1, "sub_acesso": 68.45, "sub_qualidade": 55.72}, {"ano": 2021, "icvs": 64.54, "icvs_quintil": 4, "sub_desfechos": 75.49, "sub_acesso": 52.79, "sub_qualidade": 63.47}, {"ano": 2022, "icvs": 51.39, "icvs_quintil": 3, "sub_desfechos": 57.26, "sub_acesso": 39.69, "sub_qualidade": 58.38}, {"ano": 2023, "icvs": 51.8, "icvs_quintil": 3, "sub_desfechos": 52.98, "sub_acesso": 50.07, "sub_qualidade": 52.31}], "indicadores": [{"ano": 2023, "indicador": "tmi", "valor": 0.5391, "valor_suavizado": 0.533}, {"ano": 2023, "indicador": "rmm", "valor": 0.5138, "valor_suavizado": 0.4655}, {"ano": 2023, "indicador": "apvp_taxa", "valor": 0.6177, "valor_suavizado": 0.5773}, {"ano": 2023, "indicador": "mort_prematura_dcnt", "valor": 0.4305, "valor_suavizado": 0.4425}, {"ano": 2023, "indicador": "proporcao_obitos_evitaveis", "valor": 0.5119, "valor_suavizado": 0.481}, {"ano": 2023, "indicador": "cobertura_esf_inv", "valor": 0.4192, "valor_suavizado": 0.3882}, {"ano": 2023, "indicador": "cobertura_acs_inv", "valor": 0.3674, "valor_suavizado": 0.3586}, {"ano": 2023, "indicador": "leitos_sus_inv", "valor": 0.5831, "valor_suavizado": 0.6005}, {"ano": 2023, "indicador": "medicos_inv", "valor": 0.558, "valor_suavizado": 0.5632}, {"ano": 2023, "indicador": "distancia_hospital", "valor": 0.4953, "valor_suavizado": 0.5054}, {"ano": 2023, "indicador": "taxa_icsap", "valor": 0.3824, "valor_suavizado": 0.3748}, {"ano": 2023, "indicador": "taxa_cesareas_sus", "valor": 0.3389, "valor_suavizado": 0.3442}, {"ano": 2023, "indicador": "prenatal_inadequado", "valor": 0.4572, "valor_suavizado": 0.451}, {"ano": 2023, "indicador": "internacao_dm", "valor": 0.7406, "valor_suavizado": 0.7791}, {"ano": 2023, "indicador": "obitos_sem_assistencia", "valor": 0.4613, "valor_suavizado": 0.4668}]}