{"info": {"codmunicipio": "3118908", "nome": "Cordisburgo", "uf": "MG", "regiao": "Sudeste", "lat": -17.0531, "lon": -45.6767, "populacao": 4745, "icvs": 74.66, "sub_desfechos": 79.98, "sub_acesso": 71.44, "sub_qualidade": 70.66, "icvs_quintil": 5, "cluster": 2}, "icvs_historico": [{"ano": 2014, "icvs": 37.12, "icvs_quintil": 2, "sub_desfechos": 33.91, "sub_acesso": 37.59, "sub_qualidade": 41.61}, {"ano": 2015, "icvs": 45.95, "icvs_quintil": 3, "sub_desfechos": 40.43, "sub_acesso": 51.8, "sub_qualidade": 46.59}, {"ano": 2016, "icvs": 70.91, "icvs_quintil": 4, "sub_desfechos": 69.97, "sub_acesso": 69.44, "sub_qualidade": 74.45}, {"ano": 2017, "icvs": 26.32, "icvs_quintil": 2, "sub_desfechos": 20.62, "sub_acesso": 29.28, "sub_qualidade": 31.3}, {"ano": 2018, "icvs": 21.0, "icvs_quintil": 2, "sub_desfechos": 14.26, "sub_acesso": 14.91, "sub_qualidade": 40.32}, {"ano": 2019, "icvs": 17.48, "icvs_quintil": 1, "sub_desfechos": 10.07, "sub_acesso": 16.98, "sub_qualidade": 30.03}, {"ano": 2020, "icvs": 41.42, "icvs_quintil": 3, "sub_desfechos": 28.93, "sub_acesso": 44.21, "sub_qualidade": 57.48}, {"ano": 2021, "icvs": 55.83, "icvs_quintil": 3, "sub_desfechos": 49.7, "sub_acesso": 66.0, "sub_qualidade": 51.41}, {"ano": 2022, "icvs": 37.04, "icvs_quintil": 2, "sub_desfechos": 32.69, "sub_acesso": 34.59, "sub_qualidade": 47.43}, {"ano": 2023, "icvs": 50.73, "icvs_quintil": 3, "sub_desfechos": 55.37, "sub_acesso": 50.69, "sub_qualidade": 43.35}], "indicadores": [{"ano": 2023, "indicador": "tmi", "valor": 0.2945, "valor_suavizado": 0.2399}, {"ano": 2023, "indicador": "rmm", "valor": 0.4751, "valor_suavizado": 0.4665}, {"ano": 2023, "indicador": "apvp_taxa", "valor": 0.5135, "valor_suavizado": 0.5172}, {"ano": 2023, "indicador": "mort_prematura_dcnt", "valor": 0.3194, "valor_suavizado": 0.3098}, {"ano": 2023, "indicador": "proporcao_obitos_evitaveis", "valor": 0.3004, "valor_suavizado": 0.3017}, {"ano": 2023, "indicador": "cobertura_esf_inv", "valor": 0.4666, "valor_suavizado": 0.4648}, {"ano": 2023, "indicador": "cobertura_acs_inv", "valor": 0.4912, "valor_suavizado": 0.4809}, {"ano": 2023, "indicador": "leitos_sus_inv", "valor": 0.4738, "valor_suavizado": 0.4587}, {"ano": 2023, "indicador": "medicos_inv", "valor": 0.3711, "valor_suavizado": 0.4057}, {"ano": 2023, "indicador": "distancia_hospital", "valor": 0.4169, "valor_suavizado": 0.4338}, {"ano": 2023, "indicador": "taxa_icsap", "valor": 0.071, "valor_suavizado": 0.0825}, {"ano": 2023, "indicador": "taxa_cesareas_sus", "valor": 0.4708, "valor_suavizado": 0.4616}, {"ano": 2023, "indicador": "prenatal_inadequado", "valor": 0.6168, "valor_suavizado": 0.5659}, {"ano": 2023, "indicador": "internacao_dm", "valor": 0.4545, "valor_suavizado": 0.4723}, {"ano": 2023, "indicador": "obitos_sem_assistencia", "valor": 0.2233, "valor_suavizado": 0.2515}]}