{"info": {"codmunicipio": "3170057", "nome": "Ubaporanga", "uf": "MG", "regiao": "Sudeste", "lat": -18.514, "lon": -42.1189, "populacao": 5426, "icvs": 46.26, "sub_desfechos": 41.19, "sub_acesso": 50.85, "sub_qualidade": 47.95, "icvs_quintil": 3, "cluster": 2}, "icvs_historico": [{"ano": 2014, "icvs": 71.09, "icvs_quintil": 4, "sub_desfechos": 63.07, "sub_acesso": 81.13, "sub_qualidade": 69.86}, {"ano": 2015, "icvs": 32.69, "icvs_quintil": 2, "sub_desfechos": 23.98, "sub_acesso": 35.55, "sub_qualidade": 42.6}, {"ano": 2016, "icvs": 49.4, "icvs_quintil": 3, "sub_desfechos": 45.97, "sub_acesso": 44.3, "sub_qualidade": 62.04}, {"ano": 2017, "icvs": 39.13, "icvs_quintil": 2, "sub_desfechos": 31.16, "sub_acesso": 40.09, "sub_qualidade": 50.53}, {"ano": 2018, "icvs": 16.97, "icvs_quintil": 1, "sub_desfechos": 19.68, "sub_acesso": 9.0, "sub_qualidade": 23.78}, {"ano": 2019, "icvs": 15.02, "icvs_quintil": 1, "sub_desfechos": 10.86, "sub_acesso": 10.14, "sub_qualidade": 28.51}, {"ano": 2020, "icvs": 25.39, "icvs_quintil": 2, "sub_desfechos": 19.46, "sub_acesso": 32.52, "sub_qualidade": 24.91}, {"ano": 2021, "icvs": 56.31, "icvs_quintil": 3, "sub_desfechos": 58.03, "sub_acesso": 54.76, "sub_qualidade": 55.72}, {"ano": 2022, "icvs": 14.34, "icvs_quintil": 1, "sub_desfechos": 27.18, "sub_acesso": 9.62, "sub_qualidade": 0.41}, {"ano": 2023, "icvs": 20.35, "icvs_quintil": 2, "sub_desfechos": 27.15, "sub_acesso": 7.73, "sub_qualidade": 27.15}], "indicadores": [{"ano": 2023, "indicador": "tmi", "valor": 0.5608, "valor_suavizado": 0.5404}, {"ano": 2023, "indicador": "rmm", "valor": 0.5825, "valor_suavizado": 0.5656}, {"ano": 2023, "indicador": "apvp_taxa", "valor": 0.5555, "valor_suavizado": 0.5762}, {"ano": 2023, "indicador": "mort_prematura_dcnt", "valor": 0.3748, "valor_suavizado": 0.3854}, {"ano": 2023, "indicador": "proporcao_obitos_evitaveis", "valor": 0.474, "valor_suavizado": 0.4386}, {"ano": 2023, "indicador": "cobertura_esf_inv", "valor": 0.3233, "valor_suavizado": 0.2899}, {"ano": 2023, "indicador": "cobertura_acs_inv", "valor": 0.589, "valor_suavizado": 0.6189}, {"ano": 2023, "indicador": "leitos_sus_inv", "valor": 0.3479, "valor_suavizado": 0.3337}, {"ano": 2023, "indicador": "medicos_inv", "valor": 0.4905, "valor_suavizado": 0.4805}, {"ano": 2023, "indicador": "distancia_hospital", "valor": 0.4822, "valor_suavizado": 0.4688}, {"ano": 2023, "indicador": "taxa_icsap", "valor": 0.3039, "valor_suavizado": 0.2935}, {"ano": 2023, "indicador": "taxa_cesareas_sus", "valor": 0.4452, "valor_suavizado": 0.4089}, {"ano": 2023, "indicador": "prenatal_inadequado", "valor": 0.5968, "valor_suavizado": 0.5989}, {"ano": 2023, "indicador": "internacao_dm", "valor": 0.5104, "valor_suavizado": 0.5437}, {"ano": 2023, "indicador": "obitos_sem_assistencia", "valor": 0.4762, "valor_suavizado": 0.4954}]}