{"info": {"codmunicipio": "3555703", "nome": "União Paulista", "uf": "SP", "regiao": "Sudeste", "lat": -20.7371, "lon": -47.3311, "populacao": 12737, "icvs": 40.08, "sub_desfechos": 37.49, "sub_acesso": 46.55, "sub_qualidade": 35.16, "icvs_quintil": 3, "cluster": 2}, "icvs_historico": [{"ano": 2014, "icvs": 22.34, "icvs_quintil": 2, "sub_desfechos": 20.09, "sub_acesso": 13.54, "sub_qualidade": 38.28}, {"ano": 2015, "icvs": 30.73, "icvs_quintil": 2, "sub_desfechos": 28.75, "sub_acesso": 28.68, "sub_qualidade": 36.78}, {"ano": 2016, "icvs": 53.59, "icvs_quintil": 3, "sub_desfechos": 68.07, "sub_acesso": 45.44, "sub_qualidade": 41.84}, {"ano": 2017, "icvs": 36.94, "icvs_quintil": 2, "sub_desfechos": 48.72, "sub_acesso": 33.55, "sub_qualidade": 22.85}, {"ano": 2018, "icvs": 54.99, "icvs_quintil": 3, "sub_desfechos": 57.64, "sub_acesso": 56.18, "sub_qualidade": 49.09}, {"ano": 2019, "icvs": 15.57, "icvs_quintil": 1, "sub_desfechos": 13.2, "sub_acesso": 21.17, "sub_qualidade": 11.52}, {"ano": 2020, "icvs": 55.47, "icvs_quintil": 3, "sub_desfechos": 47.92, "sub_acesso": 65.14, "sub_qualidade": 53.99}, {"ano": 2021, "icvs": 51.27, "icvs_quintil": 3, "sub_desfechos": 54.32, "sub_acesso": 42.16, "sub_qualidade": 59.12}, {"ano": 2022, "icvs": 27.09, "icvs_quintil": 2, "sub_desfechos": 21.03, "sub_acesso": 33.41, "sub_qualidade": 27.95}, {"ano": 2023, "icvs": 38.55, "icvs_quintil": 2, "sub_desfechos": 40.56, "sub_acesso": 35.38, "sub_qualidade": 39.75}], "indicadores": [{"ano": 2023, "indicador": "tmi", "valor": 0.585, "valor_suavizado": 0.6047}, {"ano": 2023, "indicador": "rmm", "valor": 0.6476, "valor_suavizado": 0.6304}, {"ano": 2023, "indicador": "apvp_taxa", "valor": 0.2678, "valor_suavizado": 0.2461}, {"ano": 2023, "indicador": "mort_prematura_dcnt", "valor": 0.4895, "valor_suavizado": 0.5103}, {"ano": 2023, "indicador": "proporcao_obitos_evitaveis", "valor": 0.8758, "valor_suavizado": 0.8923}, {"ano": 2023, "indicador": "cobertura_esf_inv", "valor": 0.8148, "valor_suavizado": 0.8048}, {"ano": 2023, "indicador": "cobertura_acs_inv", "valor": 0.4236, "valor_suavizado": 0.4046}, {"ano": 2023, "indicador": "leitos_sus_inv", "valor": 0.5363, "valor_suavizado": 0.5216}, {"ano": 2023, "indicador": "medicos_inv", "valor": 0.6202, "valor_suavizado": 0.5671}, {"ano": 2023, "indicador": "distancia_hospital", "valor": 0.3787, "valor_suavizado": 0.3803}, {"ano": 2023, "indicador": "taxa_icsap", "valor": 0.6852, "valor_suavizado": 0.6655}, {"ano": 2023, "indicador": "taxa_cesareas_sus", "valor": 0.6525, "valor_suavizado": 0.6804}, {"ano": 2023, "indicador": "prenatal_inadequado", "valor": 0.5944, "valor_suavizado": 0.5841}, {"ano": 2023, "indicador": "internacao_dm", "valor": 0.4876, "valor_suavizado": 0.5136}, {"ano": 2023, "indicador": "obitos_sem_assistencia", "valor": 0.6114, "valor_suavizado": 0.6047}]}