{"info": {"codmunicipio": "411390", "nome": "Mallet", "uf": "PR", "regiao": "Sul", "populacao": 13697, "icvs": 81.36, "sub_desfechos": 100.0, "sub_acesso": 48.6, "sub_qualidade": 97.41, "icvs_quintil": 5, "cluster": 5}, "icvs_historico": [{"ano": 2021, "icvs": 81.36, "icvs_quintil": 5, "sub_desfechos": 100.0, "sub_acesso": 48.6, "sub_qualidade": 97.41}], "indicadores": [{"ano": 2021, "indicador": "tmi", "valor": 13.33, "valor_suavizado": 0.02}, {"ano": 2021, "indicador": "rmm", "valor": 666.67, "valor_suavizado": 0.01}, {"ano": 2021, "indicador": "apvp_taxa", "valor": 97.76, "valor_suavizado": 97.76}, {"ano": 2021, "indicador": "mort_prematura_dcnt", "valor": 405.6, "valor_suavizado": 405.6}, {"ano": 2021, "indicador": "proporcao_obitos_evitaveis", "valor": 0.19, "valor_suavizado": 0.19}, {"ano": 2021, "indicador": "cobertura_esf_inv", "valor": null, "valor_suavizado": null}, {"ano": 2021, "indicador": "cobertura_acs_inv", "valor": null, "valor_suavizado": null}, {"ano": 2021, "indicador": "leitos_sus_inv", "valor": 2.41, "valor_suavizado": 2.41}, {"ano": 2021, "indicador": "medicos_inv", "valor": 0.8, "valor_suavizado": 0.8}, {"ano": 2021, "indicador": "distancia_hospital", "valor": null, "valor_suavizado": null}, {"ano": 2021, "indicador": "taxa_icsap", "valor": 148.21, "valor_suavizado": 148.21}, {"ano": 2021, "indicador": "taxa_cesareas_sus", "valor": 0.61, "valor_suavizado": 0.61}, {"ano": 2021, "indicador": "prenatal_inadequado", "valor": 0.03, "valor_suavizado": 0.03}, {"ano": 2021, "indicador": "internacao_dm", "valor": 6.57, "valor_suavizado": 6.57}, {"ano": 2021, "indicador": "obitos_sem_assistencia", "valor": 0.22, "valor_suavizado": 0.22}]}