{"info": {"codmunicipio": "420960", "nome": "Lauro Müller", "uf": "SC", "regiao": "Sul", "populacao": 15380, "icvs": 72.59, "sub_desfechos": 100.0, "sub_acesso": 36.13, "sub_qualidade": 79.78, "icvs_quintil": 5, "cluster": 5}, "icvs_historico": [{"ano": 2021, "icvs": 72.59, "icvs_quintil": 5, "sub_desfechos": 100.0, "sub_acesso": 36.13, "sub_qualidade": 79.78}], "indicadores": [{"ano": 2021, "indicador": "tmi", "valor": 10.99, "valor_suavizado": 0.01}, {"ano": 2021, "indicador": "rmm", "valor": 549.45, "valor_suavizado": 0.01}, {"ano": 2021, "indicador": "apvp_taxa", "valor": 128.67, "valor_suavizado": 128.67}, {"ano": 2021, "indicador": "mort_prematura_dcnt", "valor": 592.4, "valor_suavizado": 592.4}, {"ano": 2021, "indicador": "proporcao_obitos_evitaveis", "valor": 0.12, "valor_suavizado": 0.12}, {"ano": 2021, "indicador": "cobertura_esf_inv", "valor": null, "valor_suavizado": null}, {"ano": 2021, "indicador": "cobertura_acs_inv", "valor": null, "valor_suavizado": null}, {"ano": 2021, "indicador": "leitos_sus_inv", "valor": 2.6, "valor_suavizado": 2.6}, {"ano": 2021, "indicador": "medicos_inv", "valor": 1.69, "valor_suavizado": 1.69}, {"ano": 2021, "indicador": "distancia_hospital", "valor": null, "valor_suavizado": null}, {"ano": 2021, "indicador": "taxa_icsap", "valor": 104.03, "valor_suavizado": 104.03}, {"ano": 2021, "indicador": "taxa_cesareas_sus", "valor": 0.78, "valor_suavizado": 0.78}, {"ano": 2021, "indicador": "prenatal_inadequado", "valor": 0.03, "valor_suavizado": 0.03}, {"ano": 2021, "indicador": "internacao_dm", "valor": 2.6, "valor_suavizado": 2.6}, {"ano": 2021, "indicador": "obitos_sem_assistencia", "valor": 0.14, "valor_suavizado": 0.14}]}