{"info": {"codmunicipio": "4305124", "nome": "Cerrito", "uf": "RS", "regiao": "Sul", "lat": -30.69, "lon": -53.1155, "populacao": 44878, "icvs": 33.54, "sub_desfechos": 42.28, "sub_acesso": 20.38, "sub_qualidade": 37.98, "icvs_quintil": 2, "cluster": 4}, "icvs_historico": [{"ano": 2014, "icvs": 45.79, "icvs_quintil": 3, "sub_desfechos": 44.49, "sub_acesso": 50.75, "sub_qualidade": 40.92}, {"ano": 2015, "icvs": 37.26, "icvs_quintil": 2, "sub_desfechos": 45.05, "sub_acesso": 26.32, "sub_qualidade": 40.11}, {"ano": 2016, "icvs": 59.64, "icvs_quintil": 3, "sub_desfechos": 60.85, "sub_acesso": 65.87, "sub_qualidade": 49.0}, {"ano": 2017, "icvs": 32.7, "icvs_quintil": 2, "sub_desfechos": 34.38, "sub_acesso": 37.57, "sub_qualidade": 23.21}, {"ano": 2018, "icvs": 56.6, "icvs_quintil": 3, "sub_desfechos": 49.31, "sub_acesso": 73.77, "sub_qualidade": 44.21}, {"ano": 2019, "icvs": 19.3, "icvs_quintil": 1, "sub_desfechos": 22.35, "sub_acesso": 13.78, "sub_qualidade": 22.15}, {"ano": 2020, "icvs": 39.02, "icvs_quintil": 2, "sub_desfechos": 50.78, "sub_acesso": 23.65, "sub_qualidade": 41.74}, {"ano": 2021, "icvs": 24.4, "icvs_quintil": 2, "sub_desfechos": 25.32, "sub_acesso": 15.73, "sub_qualidade": 35.06}, {"ano": 2022, "icvs": 34.82, "icvs_quintil": 2, "sub_desfechos": 38.58, "sub_acesso": 26.47, "sub_qualidade": 40.51}, {"ano": 2023, "icvs": 18.42, "icvs_quintil": 1, "sub_desfechos": 18.07, "sub_acesso": 19.51, "sub_qualidade": 17.46}], "indicadores": [{"ano": 2023, "indicador": "tmi", "valor": 0.1222, "valor_suavizado": 0.1106}, {"ano": 2023, "indicador": "rmm", "valor": 0.424, "valor_suavizado": 0.4171}, {"ano": 2023, "indicador": "apvp_taxa", "valor": 0.3782, "valor_suavizado": 0.3718}, {"ano": 2023, "indicador": "mort_prematura_dcnt", "valor": 0.1239, "valor_suavizado": 0.1391}, {"ano": 2023, "indicador": "proporcao_obitos_evitaveis", "valor": 0.2719, "valor_suavizado": 0.2474}, {"ano": 2023, "indicador": "cobertura_esf_inv", "valor": 0.2213, "valor_suavizado": 0.2093}, {"ano": 2023, "indicador": "cobertura_acs_inv", "valor": 0.2853, "valor_suavizado": 0.2894}, {"ano": 2023, "indicador": "leitos_sus_inv", "valor": 0.2264, "valor_suavizado": 0.2302}, {"ano": 2023, "indicador": "medicos_inv", "valor": 0, "valor_suavizado": 0}, {"ano": 2023, "indicador": "distancia_hospital", "valor": 0.263, "valor_suavizado": 0.2751}, {"ano": 2023, "indicador": "taxa_icsap", "valor": 0.4015, "valor_suavizado": 0.4089}, {"ano": 2023, "indicador": "taxa_cesareas_sus", "valor": 0.2399, "valor_suavizado": 0.2543}, {"ano": 2023, "indicador": "prenatal_inadequado", "valor": 0.1837, "valor_suavizado": 0.1982}, {"ano": 2023, "indicador": "internacao_dm", "valor": 0.1772, "valor_suavizado": 0.184}, {"ano": 2023, "indicador": "obitos_sem_assistencia", "valor": 0.2955, "valor_suavizado": 0.3017}]}