{"info": {"codmunicipio": "4307104", "nome": "Herval", "uf": "RS", "regiao": "Sul", "lat": -27.3004, "lon": -51.2202, "populacao": 30686, "icvs": 20.27, "sub_desfechos": 20.1, "sub_acesso": 13.71, "sub_qualidade": 29.72, "icvs_quintil": 1, "cluster": 4}, "icvs_historico": [{"ano": 2014, "icvs": 56.72, "icvs_quintil": 3, "sub_desfechos": 66.37, "sub_acesso": 55.29, "sub_qualidade": 43.27}, {"ano": 2015, "icvs": 20.96, "icvs_quintil": 2, "sub_desfechos": 26.77, "sub_acesso": 5.2, "sub_qualidade": 33.71}, {"ano": 2016, "icvs": 34.39, "icvs_quintil": 2, "sub_desfechos": 39.17, "sub_acesso": 29.44, "sub_qualidade": 33.67}, {"ano": 2017, "icvs": 17.96, "icvs_quintil": 1, "sub_desfechos": 23.78, "sub_acesso": 17.91, "sub_qualidade": 8.71}, {"ano": 2018, "icvs": 18.07, "icvs_quintil": 1, "sub_desfechos": 16.7, "sub_acesso": 12.77, "sub_qualidade": 27.69}, {"ano": 2019, "icvs": 4.09, "icvs_quintil": 1, "sub_desfechos": 10.23, "sub_acesso": 0, "sub_qualidade": 0}, {"ano": 2020, "icvs": 44.26, "icvs_quintil": 3, "sub_desfechos": 56.23, "sub_acesso": 25.02, "sub_qualidade": 52.04}, {"ano": 2021, "icvs": 9.41, "icvs_quintil": 1, "sub_desfechos": 10.43, "sub_acesso": 14.95, "sub_qualidade": 0}, {"ano": 2022, "icvs": 32.82, "icvs_quintil": 2, "sub_desfechos": 38.96, "sub_acesso": 25.53, "sub_qualidade": 33.2}, {"ano": 2023, "icvs": 23.88, "icvs_quintil": 2, "sub_desfechos": 19.38, "sub_acesso": 33.24, "sub_qualidade": 17.95}], "indicadores": [{"ano": 2023, "indicador": "tmi", "valor": 0.5163, "valor_suavizado": 0.4747}, {"ano": 2023, "indicador": "rmm", "valor": 0.6461, "valor_suavizado": 0.6044}, {"ano": 2023, "indicador": "apvp_taxa", "valor": 0.6887, "valor_suavizado": 0.7184}, {"ano": 2023, "indicador": "mort_prematura_dcnt", "valor": 0.3914, "valor_suavizado": 0.4052}, {"ano": 2023, "indicador": "proporcao_obitos_evitaveis", "valor": 0.33, "valor_suavizado": 0.3232}, {"ano": 2023, "indicador": "cobertura_esf_inv", "valor": 0.3678, "valor_suavizado": 0.3537}, {"ano": 2023, "indicador": "cobertura_acs_inv", "valor": 0.5383, "valor_suavizado": 0.5228}, {"ano": 2023, "indicador": "leitos_sus_inv", "valor": 0.631, "valor_suavizado": 0.6483}, {"ano": 2023, "indicador": "medicos_inv", "valor": 0.4782, "valor_suavizado": 0.4727}, {"ano": 2023, "indicador": "distancia_hospital", "valor": 0.6625, "valor_suavizado": 0.6405}, {"ano": 2023, "indicador": "taxa_icsap", "valor": 0.4626, "valor_suavizado": 0.4519}, {"ano": 2023, "indicador": "taxa_cesareas_sus", "valor": 0.7548, "valor_suavizado": 0.7456}, {"ano": 2023, "indicador": "prenatal_inadequado", "valor": 0.4029, "valor_suavizado": 0.4194}, {"ano": 2023, "indicador": "internacao_dm", "valor": 0.5254, "valor_suavizado": 0.5266}, {"ano": 2023, "indicador": "obitos_sem_assistencia", "valor": 0.5816, "valor_suavizado": 0.5762}]}