{"info": {"codmunicipio": "430807", "nome": "Fazenda Vilanova", "uf": "RS", "regiao": "Sul", "populacao": 4680, "icvs": 49.41, "sub_desfechos": 50.12, "sub_acesso": 82.59, "sub_qualidade": 1.81, "icvs_quintil": 5, "cluster": 4}, "icvs_historico": [{"ano": 2021, "icvs": 49.41, "icvs_quintil": 5, "sub_desfechos": 50.12, "sub_acesso": 82.59, "sub_qualidade": 1.81}], "indicadores": [{"ano": 2021, "indicador": "tmi", "valor": 18.52, "valor_suavizado": 0.03}, {"ano": 2021, "indicador": "rmm", "valor": 0.0, "valor_suavizado": 0.0}, {"ano": 2021, "indicador": "apvp_taxa", "valor": 162.18, "valor_suavizado": 0.17}, {"ano": 2021, "indicador": "mort_prematura_dcnt", "valor": 474.83, "valor_suavizado": 474.83}, {"ano": 2021, "indicador": "proporcao_obitos_evitaveis", "valor": 0.16, "valor_suavizado": 0.16}, {"ano": 2021, "indicador": "cobertura_esf_inv", "valor": null, "valor_suavizado": null}, {"ano": 2021, "indicador": "cobertura_acs_inv", "valor": null, "valor_suavizado": null}, {"ano": 2021, "indicador": "leitos_sus_inv", "valor": 0.0, "valor_suavizado": 0.0}, {"ano": 2021, "indicador": "medicos_inv", "valor": 1.71, "valor_suavizado": 1.71}, {"ano": 2021, "indicador": "distancia_hospital", "valor": null, "valor_suavizado": null}, {"ano": 2021, "indicador": "taxa_icsap", "valor": 47.01, "valor_suavizado": 0.01}, {"ano": 2021, "indicador": "taxa_cesareas_sus", "valor": 0.61, "valor_suavizado": 0.61}, {"ano": 2021, "indicador": "prenatal_inadequado", "valor": 0.0, "valor_suavizado": 0.0}, {"ano": 2021, "indicador": "internacao_dm", "valor": 0.0, "valor_suavizado": 0.0}, {"ano": 2021, "indicador": "obitos_sem_assistencia", "valor": 0.12, "valor_suavizado": 0.12}]}