{"info": {"codmunicipio": "4317202", "nome": "Santa Rosa", "uf": "RS", "regiao": "Sul", "lat": -29.5413, "lon": -55.06, "populacao": 13160, "icvs": 35.7, "sub_desfechos": 36.87, "sub_acesso": 36.94, "sub_qualidade": 32.07, "icvs_quintil": 2, "cluster": 2}, "icvs_historico": [{"ano": 2014, "icvs": 25.36, "icvs_quintil": 2, "sub_desfechos": 24.49, "sub_acesso": 27.9, "sub_qualidade": 23.21}, {"ano": 2015, "icvs": 42.21, "icvs_quintil": 3, "sub_desfechos": 56.47, "sub_acesso": 28.75, "sub_qualidade": 38.23}, {"ano": 2016, "icvs": 15.92, "icvs_quintil": 1, "sub_desfechos": 8.14, "sub_acesso": 8.61, "sub_qualidade": 38.59}, {"ano": 2017, "icvs": 35.83, "icvs_quintil": 2, "sub_desfechos": 38.7, "sub_acesso": 35.88, "sub_qualidade": 31.18}, {"ano": 2018, "icvs": 39.67, "icvs_quintil": 2, "sub_desfechos": 38.01, "sub_acesso": 39.49, "sub_qualidade": 42.57}, {"ano": 2019, "icvs": 42.24, "icvs_quintil": 3, "sub_desfechos": 45.19, "sub_acesso": 36.82, "sub_qualidade": 45.08}, {"ano": 2020, "icvs": 43.0, "icvs_quintil": 3, "sub_desfechos": 58.3, "sub_acesso": 29.54, "sub_qualidade": 37.35}, {"ano": 2021, "icvs": 12.8, "icvs_quintil": 1, "sub_desfechos": 0, "sub_acesso": 17.7, "sub_qualidade": 26.43}, {"ano": 2022, "icvs": 51.87, "icvs_quintil": 3, "sub_desfechos": 61.81, "sub_acesso": 44.31, "sub_qualidade": 46.56}, {"ano": 2023, "icvs": 38.25, "icvs_quintil": 2, "sub_desfechos": 47.56, "sub_acesso": 28.02, "sub_qualidade": 37.69}], "indicadores": [{"ano": 2023, "indicador": "tmi", "valor": 0.2122, "valor_suavizado": 0.2085}, {"ano": 2023, "indicador": "rmm", "valor": 0.2395, "valor_suavizado": 0.2608}, {"ano": 2023, "indicador": "apvp_taxa", "valor": 0.2345, "valor_suavizado": 0.236}, {"ano": 2023, "indicador": "mort_prematura_dcnt", "valor": 0.278, "valor_suavizado": 0.2638}, {"ano": 2023, "indicador": "proporcao_obitos_evitaveis", "valor": 0.084, "valor_suavizado": 0.0942}, {"ano": 2023, "indicador": "cobertura_esf_inv", "valor": 0.2484, "valor_suavizado": 0.259}, {"ano": 2023, "indicador": "cobertura_acs_inv", "valor": 0.2197, "valor_suavizado": 0.2419}, {"ano": 2023, "indicador": "leitos_sus_inv", "valor": 0.1248, "valor_suavizado": 0.1109}, {"ano": 2023, "indicador": "medicos_inv", "valor": 0.2336, "valor_suavizado": 0.2297}, {"ano": 2023, "indicador": "distancia_hospital", "valor": 0.158, "valor_suavizado": 0.1363}, {"ano": 2023, "indicador": "taxa_icsap", "valor": 0.1507, "valor_suavizado": 0.156}, {"ano": 2023, "indicador": "taxa_cesareas_sus", "valor": 0.3857, "valor_suavizado": 0.3634}, {"ano": 2023, "indicador": "prenatal_inadequado", "valor": 0.1203, "valor_suavizado": 0.1152}, {"ano": 2023, "indicador": "internacao_dm", "valor": 0.0983, "valor_suavizado": 0.1165}, {"ano": 2023, "indicador": "obitos_sem_assistencia", "valor": 0.0512, "valor_suavizado": 0.0456}]}