{"info": {"codmunicipio": "5205513", "nome": "Cocalzinho de Goiás", "uf": "GO", "regiao": "Centro-Oeste", "lat": -16.8528, "lon": -47.9804, "populacao": 2709, "icvs": 20.3, "sub_desfechos": 30.9, "sub_acesso": 0, "sub_qualidade": 31.75, "icvs_quintil": 1, "cluster": 4}, "icvs_historico": [{"ano": 2014, "icvs": 31.39, "icvs_quintil": 2, "sub_desfechos": 29.0, "sub_acesso": 15.92, "sub_qualidade": 56.89}, {"ano": 2015, "icvs": 52.83, "icvs_quintil": 3, "sub_desfechos": 59.01, "sub_acesso": 54.07, "sub_qualidade": 41.21}, {"ano": 2016, "icvs": 57.93, "icvs_quintil": 3, "sub_desfechos": 62.43, "sub_acesso": 51.68, "sub_qualidade": 59.46}, {"ano": 2017, "icvs": 43.84, "icvs_quintil": 3, "sub_desfechos": 42.27, "sub_acesso": 56.44, "sub_qualidade": 28.68}, {"ano": 2018, "icvs": 43.22, "icvs_quintil": 3, "sub_desfechos": 31.81, "sub_acesso": 49.57, "sub_qualidade": 52.56}, {"ano": 2019, "icvs": 57.24, "icvs_quintil": 3, "sub_desfechos": 64.42, "sub_acesso": 40.96, "sub_qualidade": 68.53}, {"ano": 2020, "icvs": 58.23, "icvs_quintil": 3, "sub_desfechos": 52.59, "sub_acesso": 79.05, "sub_qualidade": 38.11}, {"ano": 2021, "icvs": 81.58, "icvs_quintil": 5, "sub_desfechos": 68.93, "sub_acesso": 98.84, "sub_qualidade": 77.66}, {"ano": 2022, "icvs": 55.15, "icvs_quintil": 3, "sub_desfechos": 44.05, "sub_acesso": 70.55, "sub_qualidade": 51.36}, {"ano": 2023, "icvs": 49.57, "icvs_quintil": 3, "sub_desfechos": 43.31, "sub_acesso": 53.31, "sub_qualidade": 54.36}], "indicadores": [{"ano": 2023, "indicador": "tmi", "valor": 0.6146, "valor_suavizado": 0.6075}, {"ano": 2023, "indicador": "rmm", "valor": 0.3617, "valor_suavizado": 0.3871}, {"ano": 2023, "indicador": "apvp_taxa", "valor": 0.4372, "valor_suavizado": 0.4623}, {"ano": 2023, "indicador": "mort_prematura_dcnt", "valor": 0.6602, "valor_suavizado": 0.6834}, {"ano": 2023, "indicador": "proporcao_obitos_evitaveis", "valor": 0.5785, "valor_suavizado": 0.5888}, {"ano": 2023, "indicador": "cobertura_esf_inv", "valor": 0.6062, "valor_suavizado": 0.6085}, {"ano": 2023, "indicador": "cobertura_acs_inv", "valor": 0.6514, "valor_suavizado": 0.6775}, {"ano": 2023, "indicador": "leitos_sus_inv", "valor": 0.6158, "valor_suavizado": 0.5728}, {"ano": 2023, "indicador": "medicos_inv", "valor": 0.684, "valor_suavizado": 0.7291}, {"ano": 2023, "indicador": "distancia_hospital", "valor": 0.5209, "valor_suavizado": 0.5362}, {"ano": 2023, "indicador": "taxa_icsap", "valor": 0.5621, "valor_suavizado": 0.5616}, {"ano": 2023, "indicador": "taxa_cesareas_sus", "valor": 0.5272, "valor_suavizado": 0.5414}, {"ano": 2023, "indicador": "prenatal_inadequado", "valor": 0.548, "valor_suavizado": 0.56}, {"ano": 2023, "indicador": "internacao_dm", "valor": 0.749, "valor_suavizado": 0.7651}, {"ano": 2023, "indicador": "obitos_sem_assistencia", "valor": 0.682, "valor_suavizado": 0.665}]}