{"info": {"codmunicipio": "5213103", "nome": "Mineiros", "uf": "GO", "regiao": "Centro-Oeste", "lat": -17.9522, "lon": -48.9262, "populacao": 10284, "icvs": 23.29, "sub_desfechos": 20.17, "sub_acesso": 28.41, "sub_qualidade": 21.14, "icvs_quintil": 1, "cluster": 4}, "icvs_historico": [{"ano": 2014, "icvs": 50.02, "icvs_quintil": 3, "sub_desfechos": 48.22, "sub_acesso": 54.0, "sub_qualidade": 47.34}, {"ano": 2015, "icvs": 71.76, "icvs_quintil": 4, "sub_desfechos": 69.17, "sub_acesso": 75.81, "sub_qualidade": 70.25}, {"ano": 2016, "icvs": 55.09, "icvs_quintil": 3, "sub_desfechos": 62.97, "sub_acesso": 42.55, "sub_qualidade": 60.06}, {"ano": 2017, "icvs": 44.13, "icvs_quintil": 3, "sub_desfechos": 50.96, "sub_acesso": 29.93, "sub_qualidade": 53.07}, {"ano": 2018, "icvs": 69.13, "icvs_quintil": 4, "sub_desfechos": 74.3, "sub_acesso": 65.79, "sub_qualidade": 65.56}, {"ano": 2019, "icvs": 32.66, "icvs_quintil": 2, "sub_desfechos": 25.94, "sub_acesso": 35.37, "sub_qualidade": 39.64}, {"ano": 2020, "icvs": 26.08, "icvs_quintil": 2, "sub_desfechos": 19.25, "sub_acesso": 37.54, "sub_qualidade": 20.96}, {"ano": 2021, "icvs": 59.72, "icvs_quintil": 3, "sub_desfechos": 55.54, "sub_acesso": 65.28, "sub_qualidade": 58.62}, {"ano": 2022, "icvs": 44.72, "icvs_quintil": 3, "sub_desfechos": 44.95, "sub_acesso": 46.18, "sub_qualidade": 42.3}, {"ano": 2023, "icvs": 22.89, "icvs_quintil": 2, "sub_desfechos": 30.44, "sub_acesso": 21.27, "sub_qualidade": 13.09}], "indicadores": [{"ano": 2023, "indicador": "tmi", "valor": 0.3096, "valor_suavizado": 0.2752}, {"ano": 2023, "indicador": "rmm", "valor": 0.1806, "valor_suavizado": 0.1839}, {"ano": 2023, "indicador": "apvp_taxa", "valor": 0.2741, "valor_suavizado": 0.3096}, {"ano": 2023, "indicador": "mort_prematura_dcnt", "valor": 0.2391, "valor_suavizado": 0.2759}, {"ano": 2023, "indicador": "proporcao_obitos_evitaveis", "valor": 0.3271, "valor_suavizado": 0.3103}, {"ano": 2023, "indicador": "cobertura_esf_inv", "valor": 0.4979, "valor_suavizado": 0.5323}, {"ano": 2023, "indicador": "cobertura_acs_inv", "valor": 0.3362, "valor_suavizado": 0.3387}, {"ano": 2023, "indicador": "leitos_sus_inv", "valor": 0.0063, "valor_suavizado": 0.0414}, {"ano": 2023, "indicador": "medicos_inv", "valor": 0.3763, "valor_suavizado": 0.3819}, {"ano": 2023, "indicador": "distancia_hospital", "valor": 0.0511, "valor_suavizado": 0.0452}, {"ano": 2023, "indicador": "taxa_icsap", "valor": 0.3435, "valor_suavizado": 0.3607}, {"ano": 2023, "indicador": "taxa_cesareas_sus", "valor": 0.2926, "valor_suavizado": 0.2653}, {"ano": 2023, "indicador": "prenatal_inadequado", "valor": 0.2981, "valor_suavizado": 0.2951}, {"ano": 2023, "indicador": "internacao_dm", "valor": 0.2392, "valor_suavizado": 0.2025}, {"ano": 2023, "indicador": "obitos_sem_assistencia", "valor": 0.5671, "valor_suavizado": 0.5532}]}